dockerpycreds/utils.py
dockerpycreds/store.py
dockerpycreds/errors.py
dockerpycreds/__init__.py
dockerpycreds/version.py
dockerpycreds/constants.py
docker_pycreds-0.2.3.dist-info/top_level.txt
docker_pycreds-0.2.3.dist-info/WHEEL
docker_pycreds-0.2.3.dist-info/METADATA
docker_pycreds-0.2.3.dist-info/RECORD
docker_pycreds-0.2.3.dist-info/DESCRIPTION.rst
docker_pycreds-0.2.3.dist-info/metadata.json
